CHANGELOG
README.html
README.org
napy/__init__.py
napy/console/__init__.py
napy/console/template.py
napy/ipyext/__init__.py
napy/ipyext/b_e.py
napy/ipyext/ns.py
napy/template/__init__.py
napy/template/template.py
napy/tools/__init__.py
napy/tools/utility.py
poetry.lock
napy-0.2.2.dist-info/entry_points.txt
napy-0.2.2.dist-info/LICENSE
napy-0.2.2.dist-info/WHEEL
napy-0.2.2.dist-info/METADATA
napy-0.2.2.dist-info/RECORD
