Metadata-Version: 2.1
Name: napy
Version: 0.2.2
Summary: Here is everything frequently use in python.
Home-page: https://nasyxx.gitlab.io/napy/
License: GPL-3.0+
Keywords: crawler,math,utility,lib
Author: Nasy
Author-email: nasyxx+napy@gmail.com
Requires-Python: >=3.7,<4.0
Classifier: License :: OSI Approved :: GNU General Public License v3 (GPLv3)
Classifier: License :: OSI Approved :: GNU General Public License v3 or later (GPLv3+)
Classifier: Programming Language :: Python :: 3
Classifier: Programming Language :: Python :: 3.7
Classifier: Topic :: Software Development :: Libraries :: Python Modules
Classifier: Topic :: Utilities
Provides-Extra: all
Provides-Extra: math
Provides-Extra: others
Requires-Dist: better_exceptions (>=0.2.1,<0.3.0)
Requires-Dist: bs4 (>=0.0.1,<0.0.2); extra == "all" or extra == "others"
Requires-Dist: cleo (>=0.7.2,<0.8.0)
Requires-Dist: jupyter (>=1.0,<2.0); extra == "all" or extra == "math"
Requires-Dist: numpy (>=1.15,<2.0); extra == "all" or extra == "math"
Requires-Dist: pandas (>=0.23.4,<0.24.0); extra == "all" or extra == "math"
Requires-Dist: pendulum (>=2.0,<3.0); extra == "all" or extra == "others"
Requires-Dist: requests (>=2.21,<3.0)
Requires-Dist: requests_html (>=0.9.0,<0.10.0)
Requires-Dist: sympy (>=1.3,<2.0); extra == "all" or extra == "math"
Requires-Dist: tqdm (>=4.28,<5.0); extra == "all" or extra == "others"
Project-URL: Documentation, https://nasyxx.gitlab.io/napy/
Project-URL: Repository, https://gitlab.com/nasyxx/napy
